locate_pixelcolor_c/LICENSE
locate_pixelcolor_c/README.md
locate_pixelcolor_c/__init__.py
locate_pixelcolor_c/cloop.so
locate_pixelcolor_c/requirements.txt
locate_pixelcolor_c/thirdparty.json
locate_pixelcolor_c-0.12.dist-info/LICENSE.rst
locate_pixelcolor_c-0.12.dist-info/METADATA
locate_pixelcolor_c-0.12.dist-info/WHEEL
locate_pixelcolor_c-0.12.dist-info/top_level.txt
locate_pixelcolor_c-0.12.dist-info/RECORD
