Metadata-Version: 2.1
Name: locate-pixelcolor-c
Version: 0.12
Summary: Detects colors in images 10 x faster than Numpy 
Home-page: https://github.com/hansalemaos/locate_pixelcolor_c
Author: Johannes Fischer
Author-email: aulasparticularesdealemaosp@gmail.com
License: MIT
Keywords: C,image,search,rgb
Classifier: Development Status :: 4 - Beta
Classifier: Programming Language :: Python :: 3 :: Only
Classifier: Programming Language :: Python :: 3.10
Classifier: Topic :: Software Development :: Libraries :: Python Modules
Classifier: Topic :: Utilities
License-File: LICENSE.rst
Requires-Dist: numpy
